sakura/__init__.py
sakura/decoders/__init__.py
sakura/decoders/decoder.py
sakura/decoders/json_decoder.py
sakura/exceptions.py
sakura/logging/__init__.py
sakura/logging/logger.py
sakura/logging/loguru.py
sakura/microservice.py
sakura/providers/__init__.py
sakura/providers/provider.py
sakura/providers/rabbitmq_provider/__init__.py
sakura/providers/rabbitmq_provider/provider.py
sakura/pubsub/__init__.py
sakura/pubsub/client.py
sakura/pubsub/subscriber.py
sakura/pubsub/types.py
sakura/rabbitmq/__init__.py
sakura/rabbitmq/rabbitmq_client.py
sakura/rabbitmq/rabbitmq_subscriber.py
sakura/rabbitmq/types.py
sakura/sakura.py
sakura/settings/__init__.py
sakura/settings/settings.py
sakura/tests/__init__.py
sakura/tests/mocks.py
sakura/utils/__init__.py
sakura/utils/decorators.py
sakura/utils/factory.py
sakura/utils/types.py
sakura/utils/utils.py
sakura_core-0.1.2.dist-info/METADATA
sakura_core-0.1.2.dist-info/WHEEL
sakura_core-0.1.2.dist-info/RECORD
