Metadata-Version: 2.1
Name: sakura-core
Version: 0.1.2
Summary: 
Requires-Python: >=3.9,<4.0
Classifier: Programming Language :: Python :: 3
Classifier: Programming Language :: Python :: 3.9
Classifier: Programming Language :: Python :: 3.10
Classifier: Programming Language :: Python :: 3.11
Provides-Extra: uvloop
Requires-Dist: asyncer (>=0.0.2,<0.0.3)
Requires-Dist: dynaconf (>=3.2.0,<4.0.0)
Requires-Dist: loguru (>=0.7.0,<0.8.0)
Requires-Dist: uvloop (>=0.17.0,<0.18.0) ; extra == "uvloop"
